nb_venv_kernels/__init__.py
nb_venv_kernels/_version.py
nb_venv_kernels/cli.py
nb_venv_kernels/manager.py
nb_venv_kernels/registry.py
nb_venv_kernels/routes.py
nb_venv_kernels/runner.py
nb_venv_kernels/scan_config.json
nb_venv_kernels/tests/__init__.py
nb_venv_kernels/tests/test_api.py
nb_venv_kernels/tests/test_manager.py
nb_venv_kernels/tests/test_registry.py
nb_venv_kernels/tests/test_routes.py
nb_venv_kernels-1.2.36.data/data/etc/jupyter/jupyter_config.json
nb_venv_kernels-1.2.36.data/data/etc/jupyter/jupyter_notebook_config.d/nb_venv_kernels.json
nb_venv_kernels-1.2.36.data/data/etc/jupyter/jupyter_server_config.d/nb_venv_kernels.json
nb_venv_kernels-1.2.36.data/data/share/jupyter/labextensions/nb_venv_kernels/package.json
nb_venv_kernels-1.2.36.data/data/share/jupyter/labextensions/nb_venv_kernels/static/509.66453d054a72c104b8cb.js
nb_venv_kernels-1.2.36.data/data/share/jupyter/labextensions/nb_venv_kernels/static/728.86e8b31f1ae99c482623.js
nb_venv_kernels-1.2.36.data/data/share/jupyter/labextensions/nb_venv_kernels/static/remoteEntry.f2c9c3cf5cd50056d2f5.js
nb_venv_kernels-1.2.36.data/data/share/jupyter/labextensions/nb_venv_kernels/static/style.js
nb_venv_kernels-1.2.36.data/data/share/jupyter/labextensions/nb_venv_kernels/static/third-party-licenses.json
nb_venv_kernels-1.2.36.data/data/share/jupyter/labextensions/nb_venv_kernels/install.json
nb_venv_kernels-1.2.36.dist-info/METADATA
nb_venv_kernels-1.2.36.dist-info/WHEEL
nb_venv_kernels-1.2.36.dist-info/entry_points.txt
nb_venv_kernels-1.2.36.dist-info/licenses/LICENSE
nb_venv_kernels-1.2.36.dist-info/RECORD
